quantum_serverless/__init__.py
quantum_serverless/exception.py
quantum_serverless/quantum_serverless.py
quantum_serverless/core/__init__.py
quantum_serverless/core/constants.py
quantum_serverless/core/decorators.py
quantum_serverless/core/files.py
quantum_serverless/core/job.py
quantum_serverless/core/pattern.py
quantum_serverless/core/provider.py
quantum_serverless/core/tracing.py
quantum_serverless/library/__init__.py
quantum_serverless/library/transpiler.py
quantum_serverless/serializers/__init__.py
quantum_serverless/serializers/program_serializers.py
quantum_serverless/serializers/serializers.py
quantum_serverless/utils/__init__.py
quantum_serverless/utils/errors.py
quantum_serverless/utils/json.py
quantum_serverless/utils/storage.py
quantum_serverless/visualizaiton/__init__.py
quantum_serverless/visualizaiton/widget.py
tests/__init__.py
tests/test_quantum_serverless.py
tests/utils.py
tests/core/__init__.py
tests/core/test_decorator.py
tests/core/test_job.py
tests/core/test_pattern.py
tests/library/__init__.py
tests/library/test_transpiler.py
tests/serializers/__init__.py
tests/serializers/test_program_serializers.py
tests/serializers/test_serializers.py
quantum_serverless-0.10.1.dist-info/METADATA
quantum_serverless-0.10.1.dist-info/WHEEL
quantum_serverless-0.10.1.dist-info/top_level.txt
quantum_serverless-0.10.1.dist-info/RECORD
