Metadata-Version: 2.1
Name: quantum-serverless
Version: 0.10.1
Keywords: quantum serverless qiskit
Classifier: Development Status :: 3 - Alpha
Classifier: Intended Audience :: Developers
Classifier: Intended Audience :: Science/Research
Classifier: License :: OSI Approved :: Apache Software License
Classifier: Natural Language :: English
Classifier: Operating System :: MacOS
Classifier: Operating System :: POSIX :: Linux
Classifier: Operating System :: Microsoft :: Windows
Classifier: Programming Language :: Python :: 3.8
Classifier: Programming Language :: Python :: 3.9
Classifier: Programming Language :: Python :: 3.10
Classifier: Topic :: Scientific/Engineering :: Physics
Requires-Python: >=3.8
Requires-Dist: ray[data,default] <3,>=2.9.3
Requires-Dist: requests >=2.31.0
Requires-Dist: importlib-metadata >=5.2.0
Requires-Dist: qiskit >=1.0.2
Requires-Dist: qiskit-ibm-runtime >=0.21.1
Requires-Dist: qiskit-ibm-provider >=0.10.0
Requires-Dist: cloudpickle ==2.2.1
Requires-Dist: tqdm >=4.65.0
Requires-Dist: opentelemetry-api >=1.18.0
Requires-Dist: opentelemetry-sdk >=1.18.0
Requires-Dist: opentelemetry-exporter-otlp-proto-grpc >=1.18.0
Requires-Dist: s3fs >=2023.6.0
Requires-Dist: opentelemetry.instrumentation.requests >=0.40b0
Requires-Dist: ipywidgets >=8.1.2
Requires-Dist: ipython >=8.10.0
